office_mcp_server.py
unified_server.py
mcp_windows_automation/__init__.py
mcp_windows_server-1.0.1.dist-info/licenses/LICENSE
mcp_windows_server-1.0.1.dist-info/METADATA
mcp_windows_server-1.0.1.dist-info/WHEEL
mcp_windows_server-1.0.1.dist-info/entry_points.txt
mcp_windows_server-1.0.1.dist-info/top_level.txt
mcp_windows_server-1.0.1.dist-info/RECORD
