Metadata-Version: 2.4
Name: mcp-windows-server
Version: 1.0.1
Summary: AI-powered Windows automation framework using Model Context Protocol (MCP)
Author-email: Mahipal <mukuljangra5@gmail.com>
License-Expression: MIT
Project-URL: Homepage, https://github.com/mukul975/mcp-windows-server
Project-URL: Repository, https://github.com/mukul975/mcp-windows-server
Project-URL: Issues, https://github.com/mukul975/mcp-windows-server/issues
Project-URL: Documentation, https://github.com/mukul975/mcp-windows-server/docs
Keywords: mcp,windows,automation,ai,assistant,control,system,desktop,chatgpt,claude,protocol
Classifier: Development Status :: 4 - Beta
Classifier: Intended Audience :: Developers
Classifier: Operating System :: Microsoft :: Windows
Classifier: Programming Language :: Python :: 3
Classifier: Programming Language :: Python :: 3.10
Classifier: Programming Language :: Python :: 3.11
Classifier: Programming Language :: Python :: 3.12
Classifier: Topic :: Software Development :: Libraries :: Python Modules
Classifier: Topic :: System :: Systems Administration
Classifier: Topic :: Desktop Environment
Requires-Python: >=3.10
License-File: LICENSE
Requires-Dist: mcp>=1.0.0
Requires-Dist: psutil>=5.9.0
Requires-Dist: pillow>=10.0.0
Requires-Dist: selenium>=4.15.0
Requires-Dist: webdriver-manager>=4.0.0
Requires-Dist: opencv-python>=4.8.0
Requires-Dist: numpy>=1.24.0
Requires-Dist: requests>=2.31.0
Requires-Dist: aiohttp>=3.8.0
Requires-Dist: jsonschema>=4.17.0
Requires-Dist: colorlog>=6.7.0
Requires-Dist: click>=8.1.0
Requires-Dist: scikit-learn>=1.3.0
Requires-Dist: pandas>=2.0.0
Requires-Dist: joblib>=1.3.0
Requires-Dist: matplotlib>=3.7.0
Requires-Dist: seaborn>=0.12.0
Provides-Extra: windows
Requires-Dist: pyautogui>=0.9.54; platform_system == "Windows" and extra == "windows"
Requires-Dist: pywin32>=306; platform_system == "Windows" and extra == "windows"
Requires-Dist: tkinter-tooltip>=2.0.0; platform_system == "Windows" and extra == "windows"
Requires-Dist: customtkinter>=5.2.0; platform_system == "Windows" and extra == "windows"
Provides-Extra: dev
Requires-Dist: pytest>=7.4.0; extra == "dev"
Requires-Dist: pytest-asyncio>=0.21.0; extra == "dev"
Requires-Dist: black>=23.0.0; extra == "dev"
Requires-Dist: flake8>=6.0.0; extra == "dev"
Requires-Dist: mypy>=1.5.0; extra == "dev"
Dynamic: license-file
